jmenu/__init__.py
jmenu/__main__.py
jmenu/classes.py
jmenu/main.py
jmenu-1.10.1.dist-info/licenses/LICENSE
jmenu-1.10.1.dist-info/METADATA
jmenu-1.10.1.dist-info/WHEEL
jmenu-1.10.1.dist-info/entry_points.txt
jmenu-1.10.1.dist-info/top_level.txt
jmenu-1.10.1.dist-info/RECORD
