Metadata-Version: 2.4
Name: jmenu
Version: 1.10.1
Summary: Tool for fetching University of Oulu restaurant menus from Jamix.
Project-URL: Homepage, https://github.com/jkerola/jmenu
Project-URL: Bug Tracker, https://github.com/jkerola/jmenu/issues
Classifier: Programming Language :: Python :: 3
Classifier: License :: OSI Approved :: MIT License
Classifier: Operating System :: OS Independent
Requires-Python: >=3.10
License-File: LICENSE
Requires-Dist: requests
Dynamic: license-file
